simplebot_writefreely/__init__.py
simplebot_writefreely/orm.py
simplebot_writefreely-1.1.1.dist-info/LICENSE
simplebot_writefreely-1.1.1.dist-info/METADATA
simplebot_writefreely-1.1.1.dist-info/WHEEL
simplebot_writefreely-1.1.1.dist-info/entry_points.txt
simplebot_writefreely-1.1.1.dist-info/top_level.txt
simplebot_writefreely-1.1.1.dist-info/RECORD
