Metadata-Version: 2.1
Name: simplebot-writefreely
Version: 1.1.1
Summary: DeltaChat/WriteFreely bridge (SimpleBot plugin)
Home-page: https://github.com/simplebot-org/simplebot_writefreely
Author: The SimpleBot Contributors
Author-email: adbenitez@nauta.cu
License: MPL
Keywords: simplebot plugin deltachat writefreely bridge
Classifier: Development Status :: 4 - Beta
Classifier: Environment :: Plugins
Classifier: Programming Language :: Python :: 3
Classifier: License :: OSI Approved :: Mozilla Public License 2.0 (MPL 2.0)
Classifier: Operating System :: OS Independent
Classifier: Topic :: Utilities
License-File: LICENSE
Requires-Dist: simplebot >=2.3.0
Requires-Dist: SQLAlchemy >=1.4.26
Requires-Dist: writefreely-py >=1.2.0
Provides-Extra: dev
Requires-Dist: simplebot >=2.3.0 ; extra == 'dev'
Requires-Dist: SQLAlchemy >=1.4.26 ; extra == 'dev'
Requires-Dist: writefreely-py >=1.2.0 ; extra == 'dev'
Requires-Dist: pytest >=6.2.5 ; extra == 'dev'
Requires-Dist: requests-mock >=1.9.3 ; extra == 'dev'
Requires-Dist: black >=21.10b0 ; extra == 'dev'
Requires-Dist: mypy >=0.910 ; extra == 'dev'
Requires-Dist: isort >=5.9.3 ; extra == 'dev'
Requires-Dist: pylint >=2.11.1 ; extra == 'dev'
Requires-Dist: pylama >=7.7.1 ; extra == 'dev'
Requires-Dist: types-pkg-resources >=0.1.3 ; extra == 'dev'
Provides-Extra: test
Requires-Dist: pytest >=6.2.5 ; extra == 'test'
Requires-Dist: requests-mock >=1.9.3 ; extra == 'test'
